pathsingleton/root_path.py
pathsingleton-0.1.0.dist-info/WHEEL
pathsingleton-0.1.0.dist-info/METADATA
pathsingleton-0.1.0.dist-info/RECORD
