Metadata-Version: 2.1
Name: pathsingleton
Version: 0.1.0
Summary: Module to track the directory our program starts in.
License: MIT
Author: Yashesh Dasari
Author-email: ydasari@uwaterloo.ca
Requires-Python: >=3.4,<4.0
Classifier: License :: OSI Approved :: MIT License
Classifier: Programming Language :: Python :: 3
Classifier: Programming Language :: Python :: 3.10
Classifier: Programming Language :: Python :: 3.4
Classifier: Programming Language :: Python :: 3.5
Classifier: Programming Language :: Python :: 3.6
Classifier: Programming Language :: Python :: 3.7
Classifier: Programming Language :: Python :: 3.8
Classifier: Programming Language :: Python :: 3.9
